GRIDX/__init__.py
GRIDX/gridm/__init__.py
GRIDX/gridm/gridxy.py
GuZiX/__init__.py
GuZiX/launchtools.py
GuZiX/GIZ/DataStore.py
GuZiX/GIZ/TTN.py
GuZiX/GIZ/__init__.py
GuziX-6.0.dist-info/METADATA
GuziX-6.0.dist-info/WHEEL
GuziX-6.0.dist-info/top_level.txt
GuziX-6.0.dist-info/RECORD
